{
    "BuildTarget": "Android",
    "DesState": "STR",
    "BaseUrl": "http://g.creativecatapp.com",
    "GameName": "test",
    "PackageName": "com.gravityfortune.gravfortn",
    "BuildCode": 6,
    "Applovin_SDK_KEY": "LMmBFSE51WdkESTJtltpBCSg5i7E2oerHByZfuBmz0RH8sas13CuJ67hXd_Q5hDeJTUyhArd63GezDaRTOUC6U",
    "Applovin_REWARD_ID": "0",
    "Applovin_INTER_ID": "0",
    "Adjust_APP_ID": "0",
    "GameCode": "0",
    "Rate_ID": "0",
    "Build_path": "",
    "ZT_LoginPlatform": 0,
    "ZT_ID": "0"
}